greenguard/__init__.py
greenguard/benchmark.py
greenguard/db.py
greenguard/demo.py
greenguard/metrics.py
greenguard/pipeline.py
greenguard/results.py
greenguard/targets.py
greenguard/utils.py
greenguard/loaders/__init__.py
greenguard/loaders/csv.py
greenguard/pipelines/classes/normalize_dfs_xgb_classifier.json
greenguard/pipelines/classes/unstack_dfs_xgb_classifier.json
greenguard/pipelines/classes/unstack_double_lstm_timeseries_classifier.json
greenguard/pipelines/classes/unstack_lstm_timeseries_classifier.json
greenguard/pipelines/classes/unstack_normalize_dfs_xgb_classifier.json
greenguard/pipelines/disabled/dfs_xgb_classifier.json
greenguard/pipelines/disabled/normalize_dfs_xgb_classifier.json
greenguard/pipelines/disabled/resample_dfs_xgb_classifier.json
greenguard/pipelines/disabled/resample_normalize_dfs_xgb_classifier.json
greenguard/pipelines/disabled/resample_unstack_dfs_xgb_classifier.json
greenguard/pipelines/disabled/resample_unstack_double_lstm_timeseries_classifier.json
greenguard/pipelines/disabled/resample_unstack_lstm_timeseries_classifier.json
greenguard/pipelines/disabled/resample_unstack_normalize_dfs_xgb_classifier.json
greenguard/pipelines/probability/normalize_dfs_xgb_classifier.json
greenguard/pipelines/probability/unstack_dfs_xgb_classifier.json
greenguard/pipelines/probability/unstack_double_lstm_timeseries_classifier.json
greenguard/pipelines/probability/unstack_lstm_timeseries_classifier.json
greenguard/pipelines/probability/unstack_normalize_dfs_xgb_classifier.json
greenguard/pipelines/unstacked/unstacked_dfs_xgb_classifier.json
greenguard/pipelines/unstacked/unstacked_double_lstm_timeseries_classifier.json
greenguard/pipelines/unstacked/unstacked_lstm_timeseries_classifier.json
greenguard/pipelines/unstacked/unstacked_normalize_dfs_xgb_classifier.json
greenguard/primitives/numpy.take.json
greenguard/primitives/xgboost.XGBClassifier:probabilities.json
greenguard-1.0.0.dist-info/AUTHORS.rst
greenguard-1.0.0.dist-info/LICENSE
greenguard-1.0.0.dist-info/METADATA
greenguard-1.0.0.dist-info/WHEEL
greenguard-1.0.0.dist-info/entry_points.txt
greenguard-1.0.0.dist-info/top_level.txt
greenguard-1.0.0.dist-info/RECORD
