Metadata-Version: 2.1
Name: greenguard
Version: 1.0.0
Summary: AutoML for Renewable Energy Industries.
Home-page: https://github.com/D3-AI/GreenGuard
Author: MIT Data To AI Lab
Author-email: dailabmit@gmail.com
License: MIT license
Keywords: wind machine learning greenguard
Platform: UNKNOWN
Classifier: Development Status :: 2 - Pre-Alpha
Classifier: Intended Audience :: Developers
Classifier: License :: OSI Approved :: MIT License
Classifier: Natural Language :: English
Classifier: Programming Language :: Python :: 3
Classifier: Programming Language :: Python :: 3.6
Classifier: Programming Language :: Python :: 3.7
Classifier: Programming Language :: Python :: 3.8
Requires-Python: >=3.6,<3.9
Requires-Dist: baytune (<0.5,>=0.4.0)
Requires-Dist: mlprimitives (<0.4,>=0.3.0)
Requires-Dist: mlblocks (<0.5,>=0.4.0)
Requires-Dist: pymongo (<4,>=3.7.2)
Requires-Dist: scikit-learn (>=0.21)
Requires-Dist: tqdm (<4.50.0,>=4.36.1)
Requires-Dist: cloudpickle (<2,>=1.6)
Requires-Dist: scipy (<2,>=1.0.1)
Requires-Dist: numpy (<1.19.0,>=1.16.0)
Requires-Dist: pandas (<2,>=1)
Requires-Dist: partd (<2,>=1.1.0)
Requires-Dist: fsspec (<0.9,>=0.8.5)
Requires-Dist: dask (<3,>=2.6.0)
Requires-Dist: distributed (<3,>=2.6.0)
Requires-Dist: h5py (<2.11.0,>=2.10.0)
Requires-Dist: Keras (>=2.4)
Requires-Dist: tabulate (<0.9,>=0.8.3)
Requires-Dist: xlsxwriter (>=1.3.6<1.4)
Provides-Extra: dev
Requires-Dist: bumpversion (<0.6,>=0.5.3) ; extra == 'dev'
Requires-Dist: pip (>=9.0.1) ; extra == 'dev'
Requires-Dist: watchdog (<0.11,>=0.8.3) ; extra == 'dev'
Requires-Dist: m2r (<0.3,>=0.2.0) ; extra == 'dev'
Requires-Dist: nbsphinx (<0.7,>=0.5.0) ; extra == 'dev'
Requires-Dist: Sphinx (<3,>=1.7.1) ; extra == 'dev'
Requires-Dist: sphinx-rtd-theme (<0.5,>=0.2.4) ; extra == 'dev'
Requires-Dist: autodocsumm (>=0.1.10) ; extra == 'dev'
Requires-Dist: flake8 (<4,>=3.7.7) ; extra == 'dev'
Requires-Dist: isort (<5,>=4.3.4) ; extra == 'dev'
Requires-Dist: autoflake (<2,>=1.1) ; extra == 'dev'
Requires-Dist: autopep8 (<2,>=1.4.3) ; extra == 'dev'
Requires-Dist: twine (<4,>=1.10.0) ; extra == 'dev'
Requires-Dist: wheel (>=0.30.0) ; extra == 'dev'
Requires-Dist: coverage (<6,>=4.5.1) ; extra == 'dev'
Requires-Dist: tox (<4,>=2.9.1) ; extra == 'dev'
Requires-Dist: importlib-metadata (<2,>=0.12) ; extra == 'dev'
Requires-Dist: pytest (>=3.4.2) ; extra == 'dev'
Requires-Dist: pytest-cov (>=2.6.0) ; extra == 'dev'
Requires-Dist: jupyter (<2,>=1.0.0) ; extra == 'dev'
Requires-Dist: rundoc (<0.5,>=0.4.3) ; extra == 'dev'
Provides-Extra: test
Requires-Dist: pytest (>=3.4.2) ; extra == 'test'
Requires-Dist: pytest-cov (>=2.6.0) ; extra == 'test'
Requires-Dist: jupyter (<2,>=1.0.0) ; extra == 'test'
Requires-Dist: rundoc (<0.5,>=0.4.3) ; extra == 'test'
